{"type":"FeatureCollection","features":[{"type":"Feature","properties":{"Nombre":"Comuna de Nacimiento","Condicion":"Alerta Roja","id":"cNacimiento"},"geometry":{"type":"Point","coordinates":[-72.8249,-37.5326]}},{"type":"Feature","properties":{"Nombre":"Comuna de Cholchol","Condicion":"Alerta Roja","id":"cCholchol"},"geometry":{"type":"Point","coordinates":[-72.8704,-38.6173]}},{"type":"Feature","properties":{"Nombre":"Comuna de Lumaco","Condicion":"Alerta Roja","id":"cLumaco"},"geometry":{"type":"Point","coordinates":[-73.216,-38.3355]}},{"type":"Feature","properties":{"Nombre":"Provincia de Arauco","Condicion":"Alerta Roja","id":"pArauco"},"geometry":{"type":"Point","coordinates":[-73.5206,-37.3689]}}]}